<?xml version="1.0" encoding="UTF-8"?>
<!DOCTYPE hibernate-mapping PUBLIC "-//Hibernate/Hibernate Mapping DTD 3.0//EN" "http://www.hibernate.org/dtd/hibernate-mapping-3.0.dtd"><!--Mapping 
	file autogenerated by codefan@centit.com -->
<hibernate-mapping>
	<class name="com.centit.sys.po.TaskLog" table="P_TASK_LOG">
		<id name="taskLogId" type="java.lang.Long">
			<column name="TASK_LOG_ID" precision="12" scale="0" />
			<generator class="assigned" />
		</id>
		<property name="type" type="java.lang.String">
			<column name="TYPE" length="64" />
		</property>
		<property name="taskDesc" type="java.lang.String">
			<column name="TASK_DESC" length="2048" />
		</property>
		<property name="taskRun" type="java.lang.String">
			<column name="TASK_RUN" />
		</property>
	</class>
</hibernate-mapping>