<?xml version="1.0" encoding="UTF-8"?>
<!DOCTYPE hibernate-mapping PUBLIC "-//Hibernate/Hibernate Mapping DTD 3.0//EN" "http://www.hibernate.org/dtd/hibernate-mapping-3.0.dtd"><!--Mapping 
	file autogenerated by codefan@centit.com -->
<hibernate-mapping>
	<class name="com.centit.dispatchdoc.po.DispatchDoc" table="M_DISPATCH_DOC">
		<id name="djId" type="java.lang.String">
			<column name="NO" length="50" />
			<generator class="assigned" />
		</id>
		<property name="internalNo" type="java.lang.String">
			<column name="INTERNAL_NO" length="100"/>
		</property>
		<property name="itemId" type="java.lang.String">
			<column name="ITEM_ID" length="100"/>
		</property>
		<property name="dispatchDocNo" type="java.lang.String">
			<column name="DISPATCH_DOC_NO" length="100" />
		</property>
		<property name="dispatchDocTitle" type="java.lang.String">
			<column name="DISPATCH_DOC_TITLE" length="200" />
		</property>
		<property name="dispatchFileType" type="java.lang.String">
			<column name="DISPATCH_FILE_TYPE" length="2" />
		</property>
		<property name="dispatchDocType" type="java.lang.String">
			<column name="DISPATCH_DOC_TYPE" length="2" />
		</property>
		<property name="dispatchCanOpen" type="java.lang.String">
			<column name="DISPATCH_CAN_OPEN" />
		</property>
		<property name="dispatchOpenType" type="java.lang.String">
			<column name="DISPATCH_OPEN_TYPE" />
		</property>
		<property name="notOpenReason" type="java.lang.String">
			<column name="NOT_OPEN_REASON" length="2000" />
		</property>
		<property name="isUnionDispatch" type="java.lang.String">
			<column name="IS_UNION_DISPATCH" />
		</property>
		<property name="unionOthers" type="java.lang.String">
			<column name="UNION_OTHERS" length="1000" />
		</property>
		<property name="isCountersign" type="java.lang.String">
			<column name="IS_COUNTERSIGN" length="20"/>
		</property>
		<property name="dispatchDocSummary" type="java.lang.String">
			<column name="DISPATCH_DOC_SUMMARY" length="2000" />
		</property>
		<property name="draftDate" type="java.util.Date">
			<column name="DRAFT_DATE" length="7" />
		</property>
		<property name="optUnitName" type="java.lang.String">
			<column name="OPT_UNIT_NAME" length="400" />
		</property>
		<property name="draftUserName" type="java.lang.String">
			<column name="DRAFT_USER_NAME" length="50" />
		</property>
		<property name="secretsDegree" type="java.lang.String">
			<column name="SECRETS_DEGREE" length="2"/>
		</property>
		<property name="dispatchCopies" type="java.lang.Long">
			<column name="DISPATCH_COPIES" precision="6" scale="0" />
		</property>
		<property name="mainNotifyUnit" type="java.lang.String">
			<column name="MAIN_NOTIFY_UNIT" length="400" />
		</property>
		<property name="otherUnits" type="java.lang.String">
			<column name="OTHER_UNITS" length="1000" />
		</property>
		<property name="retentionPeriod" type="java.lang.String">
			<column name="RETENTION_PERIOD" length="7" />
		</property>
		<property name="checkUserName" type="java.lang.String">
			<column name="CHECK_USER_NAME" length="50" />
		</property>
		<property name="dispatchDocFileName" type="java.lang.String">
			<column name="DISPATCH_DOC_FILE_NAME" length="200" />
		</property>
		<property name="dispatchDocFile" type="binary" lazy="true">
			<column name="DISPATCH_DOC_FILE" />
		</property>
		<property name="createDate" type="java.util.Date">
			<column name="CREATE_DATE" length="7"/>
		</property>
		<property name="updateDate" type="java.util.Date">
			<column name="UPDATE_DATE" length="7"/>
		</property>
		<property name="syncDate" type="java.util.Date">
			<column name="SYNC_DATE" length="7" />
		</property>
		<property name="syncSign" type="java.lang.String">
			<column name="SYNC_SIGN" length="1" />
		</property>
		<property name="syncErrorDesc" type="java.lang.String">
			<column name="SYNC_ERROR_DESC" length="1000" />
		</property>
		<property name="dispatchDocRed" type="java.lang.String">
			<column name="DISPATCH_DOC_RED" length="200" />
		</property>
		<property name="printDate" type="java.util.Date">
			<column name="PRINT_DATE" length="7" />
		</property>
		<property name="criticalLevel" type="java.lang.String">
			<column name="CRITICAL_LEVEL" length="1" />
		</property>
		<property name="emergencyDegree" type="java.lang.String">
			<column name="EMERGENCY_DEGREE" length="2" />
		</property>
		<property name="commissionCanOpen" type="java.lang.String">
			<column name="COMMISSION_CAN_OPEN" />
		</property>
		<property name="unionDispatchUnits" type="java.lang.String">
			<column name="UNION_DISPATCH_UNITS" length="1000" />
		</property>
		<property name="recordId" type="java.lang.String">
			<column name="RECORDID" length="64" />
		</property>
				<property name="flowInstId" type="java.lang.Long">
			<column name="FLOWINSTID" precision="12" scale="0" />
		</property>
<!-- 		<set name="docRelatives" cascade="save-update,delete" inverse="true">
			<key>
				<column name="DISPATCH_NO" length="50" not-null="true" />
			</key>
			<one-to-many class="com.centit.dispatchdoc.po.DocRelative" />
		</set>
		<set name="docSends" cascade="save-update,delete" inverse="true">
			<key>
				<column name="NO" length="50" />
			</key>
			<one-to-many class="com.centit.dispatchdoc.po.DocSend" />
		</set>  -->
		
		<property name="dispatchcopiew" type="java.lang.Long">
			<column name="DISPATCH_COPIEW"/>
		</property>
		<property name="dispatchword" type="java.lang.String">
			<column name="DISPATCH_WORD"/>
		</property>
		<property name="dispatchUser" type="java.lang.String">
			<column name="DISPATCH_USER"/>
		</property>
		<property name="dispatchRander" type="java.lang.String">
			<column name="DISPATCH_RANDER"/>
		</property>
		<property name="dispatchTitle" type="java.lang.String">
			<column name="DISPATCH_TITLE"/>
		</property>
		<property name="isArchive" type="java.lang.String">
			<column name="ISARCHIVE"/>
		</property>
		<property name="archiveLimit" type="java.lang.String">
			<column name="ARCHIVELIMIT"/>
		</property>
		<property name="dispatchdate" type="java.util.Date">
			<column name="DISPATCH_DATE" length="7" />
		</property>
		<property name="toBeanfinishedDate" type="java.util.Date">
			<column name="TOBEANFINISHEDDATE" length="7" />
		</property>
	</class>
</hibernate-mapping>