<?xml version="1.0" encoding="UTF-8"?>
<!DOCTYPE hibernate-mapping PUBLIC "-//Hibernate/Hibernate Mapping DTD 3.0//EN" "http://www.hibernate.org/dtd/hibernate-mapping-3.0.dtd"><!--Mapping 
	file autogenerated by codefan@centit.com -->
<hibernate-mapping>
	<class name="com.centit.oa.po.OaCarinfo" table="OA_CARINFO">
		<id name="djid" type="java.lang.String">
			<column name="DJID" length="50" />
			<generator class="assigned" />
		</id>
		<property name="carno" type="java.lang.String">
			<column name="CARNO" length="50" />
		</property>
		<property name="isuse" type="java.lang.String">
			<column name="ISUSE" length="2" />
		</property>
		<property name="brand" type="java.lang.String">
			<column name="BRAND" length="40" />
		</property>
		<property name="modelType" type="java.lang.String">
			<column name="MODEL_TYPE" length="40" />
		</property>
		<property name="carType" type="java.lang.String">
			<column name="CAR_TYPE" length="20" />
		</property>
		<property name="ratifyNumber" type="java.lang.Long">
			<column name="RATIFY_NUMBER" precision="0" scale="0" />
		</property>
		<property name="ratifyLoad" type="java.lang.String">
			<column name="RATIFY_LOAD" length="40" />
		</property>
		<property name="ratifyOil" type="java.lang.String">
			<column name="RATIFY_OIL" length="40" />
		</property>
		<property name="displacement" type="java.lang.String">
			<column name="DISPLACEMENT" length="40" />
		</property>
		<property name="oilLabel" type="java.lang.String">
			<column name="OIL_LABEL" length="40" />
		</property>
		<property name="frameNumber" type="java.lang.String">
			<column name="FRAME_NUMBER" length="40" />
		</property>
		<property name="engineNo" type="java.lang.String">
			<column name="ENGINE_NO" length="40" />
		</property>
		<property name="driver" type="java.lang.String">
			<column name="DRIVER" length="32" />
		</property>
		<property name="usingNature" type="java.lang.String">
			<column name="USING_NATURE" length="20" />
		</property>
		<property name="carItems" type="java.lang.String">
			<column name="CAR_ITEMS" />
		</property>
		<property name="remark" type="java.lang.String">
			<column name="REMARK" />
		</property>
		<property name="depno" type="java.lang.String">
			<column name="DEPNO" length="40" />
		</property>
		<property name="responsibleDep" type="java.lang.String">
			<column name="RESPONSIBLE_DEP" length="40" />
		</property>
		<property name="responsiblePersion" type="java.lang.String">
			<column name="RESPONSIBLE_PERSION" length="10" />
		</property>
		<property name="carPicture" type="binary">
			<column name="CAR_PICTURE" />
		</property>
		<property name="carPictureName" type="java.lang.String">
			<column name="CAR_PICTURE_NAME" length="200" />
		</property>
		<property name="creater" type="java.lang.String">
			<column name="CREATER" length="10" />
		</property>
		<property name="createtime" type="java.util.Date">
			<column name="CREATETIME" length="7" />
		</property>
		<property name="motifytime" type="java.util.Date">
			<column name="MOTIFYTIME" length="7" />
		</property>
		<property name="driveNo" type="java.lang.String">
			<column name="driveno" length="50" />
		</property>
		<property name="rangeType" type="java.lang.String">
			<column name="range_Type" length="1" />
		</property>	
		
		<set name="oaCarApplys" cascade="save-update,delete" inverse="true">
			<key>
				<column name="CARDJID" length="50" />
			</key>
			<one-to-many class="com.centit.oa.po.OaCarApply" />
		</set>
		
		<!-- <many-to-one name="oaCommonType" class="com.centit.oa.po.OaCommonType" column="CAR_TYPE"  lazy="false" insert="false" update="false"/> -->
		
		<many-to-one name="oaDriverInfo" class="com.centit.oa.po.OaDriverInfo" column="DRIVER"   lazy="false"  insert="false" update="false"/>
	</class>
</hibernate-mapping>